dotapatch/__init__.py
dotapatch/__main__.py
dotapatch/data.py
dotapatch/model.py
dotapatch/patch.py
dotapatch/version.py
dotapatch/changelogs/706f
dotapatch/changelogs/707d
dotapatch/data/herodata
dotapatch/data/itemdata
dotapatch/templates/default
dotapatch/templates/gh-pages
dotapatch-2.4.4.data/data/dotapatch/AUTHORS.rst
dotapatch-2.4.4.data/data/dotapatch/CODE_OF_CONDUCT.rst
dotapatch-2.4.4.data/data/dotapatch/CONTRIBUTING.rst
dotapatch-2.4.4.data/data/dotapatch/LICENSE
dotapatch-2.4.4.data/data/dotapatch/requirements.txt
dotapatch-2.4.4.data/data/dotapatch/tox.ini
dotapatch-2.4.4.dist-info/METADATA
dotapatch-2.4.4.dist-info/RECORD
dotapatch-2.4.4.dist-info/WHEEL
dotapatch-2.4.4.dist-info/entry_points.txt
dotapatch-2.4.4.dist-info/top_level.txt
tests/__init__.py
tests/test_data_functions.py
tests/test_data_methods.py
tests/test_main.py
tests/test_model_methods.py
tests/test_patch.py
