Metadata-Version: 2.1
Name: dotapatch
Version: 2.4.4
Summary: Parse Dota 2 text patches to html format.
Home-page: https://github.com/arthurazs/dotapatch/
Author: Arthur Zopellaro
Author-email: arthurazsoares@gmail.com
License: MIT
Download-URL: https://github.com/arthurazs/dotapatch/archive/v2.4.4.tar.gz
Keywords: dota dota2 patch changelog html clean dotapatch convert
Platform: UNKNOWN
Classifier: Development Status :: 5 - Production/Stable
Classifier: Environment :: Console
Classifier: Intended Audience :: End Users/Desktop
Classifier: License :: OSI Approved :: MIT License
Classifier: Natural Language :: English
Classifier: Operating System :: POSIX
Classifier: Operating System :: Unix
Classifier: Programming Language :: Python
Classifier: Programming Language :: Python :: 2
Classifier: Programming Language :: Python :: 2.7
Classifier: Programming Language :: Python :: 3
Classifier: Programming Language :: Python :: 3.4
Classifier: Programming Language :: Python :: 3.5
Classifier: Programming Language :: Python :: 3.6
Classifier: Topic :: Games/Entertainment
Classifier: Topic :: Software Development :: Code Generators
Classifier: Topic :: Software Development :: Interpreters
Classifier: Topic :: Text Processing
Classifier: Topic :: Text Processing :: Markup
Classifier: Topic :: Text Processing :: Markup :: HTML
Requires-Python: >=2.7, <4
